[
    {
        "Course_Name": "[SoSe 2024] Thermische Verfahrenstechnik (LMT)",
        "Course_id": "38691",
        "Forums": [
            [
                {
                    "Forum_name": "Ankündigungen",
                    "Forum_id": "1800867",
                    "Discussions": [
                        {
                            "Discussion_Name": "Aufforderung Lehrevaluation die Zweite  ",
                            "Discussion_Id": "605409",
                            "Messages": [
                                {
                                    "Message_id": "p1086373",
                                    "Author": "Eckhard Flöter",
                                    "DateTime": "2024-07-04T07:39:03+02:00",
                                    "Content": "Falls Sie es noch nicht gemacht haben sollten, bitte kurz Ihre Meinung im untenstehenden Link kundtun.  Danke Eckhard Flöter https://befragung.tu-berlin.de/evasys/online.php?pswd=RFC1F",
                                    "Response to": "Response to nothing"
                                }
                            ]
                        },
                        {
                            "Discussion_Name": "Veranstaltung am 28.06.",
                            "Discussion_Id": "604019",
                            "Messages": [
                                {
                                    "Message_id": "p1084345",
                                    "Author": "Felix Geisendörfer",
                                    "DateTime": "2024-06-27T12:54:56+02:00",
                                    "Content": "Hallo Studierende, wir treffen uns morgen um 9:00 Uhr wieder in der Ackerstraße. Bitte bringt einen Laptop (o.ä.) mit, da wir die Berechnungen mit Excel oder entsprechender OpenOffice - Alternative durchführen werden. Viele Grüße, Felix Geisendörfer",
                                    "Response to": "Response to nothing"
                                }
                            ]
                        },
                        {
                            "Discussion_Name": "Lehrevaluation TVT - bitte Teilnehmen",
                            "Discussion_Id": "603177",
                            "Messages": [
                                {
                                    "Message_id": "p1083185",
                                    "Author": "Eckhard Flöter",
                                    "DateTime": "2024-06-24T17:31:10+02:00",
                                    "Content": "Sehr geehrte Stud*,  obligatorisch werden wir jedes Semester zur Lehrevaluation aufgefordert. Ich möchte Sie bitten den recht kurzen Fragenkatalog, nur anklicken auszufüllen. Für die Universität ist dies wichtig. Ich persönlich nehme auch Kommentare, die im Textfeld am Ende des Dokuments möglich sind ernst. Anonymität ist gesichert.  MfG Eckhard Flöter Sie können entweder über diesen Link oder den QR code auf den Fragebogen zugreifen. https://befragung.tu-berlin.de/evasys/online.php?pswd=RFC1F",
                                    "Response to": "Response to nothing"
                                }
                            ]
                        },
                        {
                            "Discussion_Name": "Veranstaltung am 21.06",
                            "Discussion_Id": "602402",
                            "Messages": [
                                {
                                    "Message_id": "p1082016",
                                    "Author": "Felix Geisendörfer",
                                    "DateTime": "2024-06-20T14:30:16+02:00",
                                    "Content": "Hallo Studierende, morgen darf ich euch wieder begrüßen. Wir treffen uns um 9 Uhr im altbekannten Hörsaal (ACK378) in der Ackerstraße. Viele Grüße, Felix Geisendörfer",
                                    "Response to": "Response to nothing"
                                }
                            ]
                        },
                        {
                            "Discussion_Name": "TVT 14 Juni",
                            "Discussion_Id": "600926",
                            "Messages": [
                                {
                                    "Message_id": "p1079914",
                                    "Author": "Susanne Rudolph-Flöter",
                                    "DateTime": "2024-06-13T16:16:30+02:00",
                                    "Content": "Hallo zusammen, morgen würden wir uns wieder um 9:00 im TK treffen. Lassen Sie mich bitte wissen, wenn Sie nicht kommen können. Danke. VG; Susanne",
                                    "Response to": "Response to nothing"
                                }
                            ]
                        },
                        {
                            "Discussion_Name": "TVT am 7. Juni 2024",
                            "Discussion_Id": "599405",
                            "Messages": [
                                {
                                    "Message_id": "p1077671",
                                    "Author": "Susanne Rudolph-Flöter",
                                    "DateTime": "2024-06-06T13:25:54+02:00",
                                    "Content": "Hallo zusammen, wir treffen uns morgen (7.6.2024) am Hauptcampus im Gebäude TK um 9:00. Wir werden ein paar kleine Experimente ausführen. Daher bitte auch Eure Laborkittel mitbringen. Ansonsten werden wir uns morgen mit dem Thema Wasseraktivität beschäftigen. Ich hoffe, wir haben morgen eine gute Veranstaltung. Bis morgen. VG; Susanne Rudolph",
                                    "Response to": "Response to nothing"
                                }
                            ]
                        },
                        {
                            "Discussion_Name": "Prüfungsplanung",
                            "Discussion_Id": "598565",
                            "Messages": [
                                {
                                    "Message_id": "p1076486",
                                    "Author": "Henriette Brykczynski",
                                    "DateTime": "2024-06-03T14:26:15+02:00",
                                    "Content": "Hallo zusammen,   Für die genaue Planung der Prüfungsmodalitäten in diesem Semester benötigen wir verbindliche Informationen, wer in diesem Semester in TVT geprüft werden möchte.   Dazu bitte bis Mittwoch, 5.6. 12 Uhr eine Mail (h.brykczynski@tu-berlin.de) oder Nachricht an mich.   Vielen Dank.   Liebe Grüße  Henriette",
                                    "Response to": "Response to nothing"
                                }
                            ]
                        },
                        {
                            "Discussion_Name": "Veranstaltung am 31.05.",
                            "Discussion_Id": "597651",
                            "Messages": [
                                {
                                    "Message_id": "p1075128",
                                    "Author": "Henriette Brykczynski",
                                    "DateTime": "2024-05-29T14:11:02+02:00",
                                    "Content": "Hallo an die aktiven TVTler:innen,   Am kommenden Freitag ist leider meine Anwesenheit in der Ackerstraße erforderlich.   Daher würde ich unseren TVT-Termin gerne hierher verlegen und hoffe, dass das für euch keine zu großen Umstände macht. Also 9 Uhr Ackerstraße 76, 13355 Berlin, 2. OG.  LG Henriette",
                                    "Response to": "Response to nothing"
                                }
                            ]
                        },
                        {
                            "Discussion_Name": "Veranstaltung am 17.05.2024",
                            "Discussion_Id": "594917",
                            "Messages": [
                                {
                                    "Message_id": "p1070891",
                                    "Author": "Henriette Brykczynski",
                                    "DateTime": "2024-05-16T12:57:31+02:00",
                                    "Content": "Hallo zusammen,   Für die morgige Veranstaltung habe ich den Wunsch vernommen, dass wir uns am Hauptcampus treffen.   Glücklicherweise ist der Seminarraum bei uns im TK morgen Vormittag nicht besetzt.  Daher können wir uns von 9-12 dort ein\"mieten\".   Also Kurzfassung: Morgen, 17.05. TVT im TK028, Start 9 Uhr. Wir gehen nicht ins Labor, ein Laptop oder andere Rechenmöglichkeit ist sicher nicht verkehrt.   Bis morgen!  LG Henriette",
                                    "Response to": "Response to nothing"
                                }
                            ]
                        },
                        {
                            "Discussion_Name": "Veranstaltung am 03.05.",
                            "Discussion_Id": "591549",
                            "Messages": [
                                {
                                    "Message_id": "p1065590",
                                    "Author": "Felix Geisendörfer",
                                    "DateTime": "2024-05-02T08:36:37+02:00",
                                    "Content": "Hallo Studierende, wie ich letzten Freitag bereits angeteasert habe, werden wir uns morgen noch einmal am Hauptcampus treffen. (Eingangsbereich TK1) Ein Laborkittel ist nicht notwendig, da wir uns in der Technikumshalle lediglich einige Geräte ansehen und anschließend die Ergebnisse von letzter Woche auswerten werden. Viele Grüße, Felix Geisendörfer",
                                    "Response to": "Response to nothing"
                                }
                            ]
                        },
                        {
                            "Discussion_Name": "Veranstaltung am 19.04.",
                            "Discussion_Id": "587374",
                            "Messages": [
                                {
                                    "Message_id": "p1059092",
                                    "Author": "Felix Geisendörfer",
                                    "DateTime": "2024-04-18T15:22:30+02:00",
                                    "Content": "Hallo Studierende, morgen beginnt Vorlesungsreihe \"Thermische Verfahrenstechnik\". Neben allgemeinen Informationen zu den Kursinhalten und der Kursorganisation werden wir morgen den ersten von 4 Themenblöcken thematisieren: Extraktion & Diffusion. Dieser erste Block besteht aus 3 Terminen und wird am 26.04. auch einen Laborvormittag beinhalten. Wir starten morgen um 9:00 Uhr in Raum ACK 378. Diesen erreicht ihr durch den Aufgang im Hof des Gebäudes. Ihr geht rechts an der Pförtnerloge vorbei und nehmt den Eingang auf der gegenüberliegenden Seite zwischen den Fahrradständern. In der 3. Etage haltet ihr euch links und findet dort den Seminarraum.  Viele Grüße, Felix Geisendörfer",
                                    "Response to": "This is the original post"
                                },
                                {
                                    "Message_id": "p1062423",
                                    "Author": "Felix Geisendörfer",
                                    "DateTime": "2024-04-24T15:54:39+02:00",
                                    "Content": "Ich habe heute Vormittag eine aktualisierte Version der Folien vom vergangenen Freitag mit einer Lösung der Aufgabe am Ende hochgeladen.",
                                    "Response to": "p1059092"
                                }
                            ]
                        },
                        {
                            "Discussion_Name": "Veranstaltung am 26.04.",
                            "Discussion_Id": "588159",
                            "Messages": [
                                {
                                    "Message_id": "p1060324",
                                    "Author": "Felix Geisendörfer",
                                    "DateTime": "2024-04-21T22:12:10+02:00",
                                    "Content": "Hallo Studierende, ab jetzt ist die Anmeldung für die Laborveranstaltung am 26.04. zum Thema Extraktion & Diffusion freigeschaltet. In Abhängigkeit der Teilnehmerzahl werden wir den Tag in einer Gruppe von 9 - 12 Uhr oder in zwei Gruppen von 8 - 12 Uhr bestreiten. Genauere Informationen und das Praktikumsskript werden nach Ablauf der Anmeldung am 24.04. zur Verfügung gestellt. Nur so viel vorab: Die Versuche werden in unseren Räumlichkeiten am Hauptcampus (TK1) stattfinden. Bitte bringt einen Laborkittel mit und lest euch alle zur Verfügung gestellten Unterlagen durch. Eine Auswertung der Versuche wird in der Veranstaltung am 03.05. erfolgen. Viele Grüße, Felix Geisendörfer",
                                    "Response to": "This is the original post"
                                },
                                {
                                    "Message_id": "p1062419",
                                    "Author": "Felix Geisendörfer",
                                    "DateTime": "2024-04-24T15:50:34+02:00",
                                    "Content": "Hallo Studierende,  da sich nur 3 Studierende gemeldet haben, werden wir die Versuche am Freitag in einer Gruppe von 9 - 12 Uhr durchführen. Bitte findet euch kurz vor 9 Uhr im Eingangsbereich des TK1 ein. (Zur Orientierung: Dort fand vor 2 Wochen der Kristallisationsversuch des LPT - Praktikum statt. Das Versuchsskript und ein Video zur Sicherheitsbelehrung habe ich heute hochgeladen. Schaut euch bitte beides vorher an, damit wir alle Versuche bis 12 Uhr schaffen können. Vor Ort wird es noch eine kurze Einweisung zu den örtlichen Sicherheitsvorkehrungen geben. Schutzbrillen sind vorhanden, ein Kittel ist mitzubringen. Bei Fragen könnt ihr euch gern bei mir melden.  Viele Grüße, Felix Geisendörfer",
                                    "Response to": "p1060324"
                                }
                            ]
                        }
                    ]
                }
            ],
            null
        ]
    }
]