[
    {
        "Course_Name": "[SoSe 2024] Energietechnik I",
        "Course_id": "38435",
        "Forums": [
            [
                {
                    "Forum_name": "Ankündigungen",
                    "Forum_id": "1791695",
                    "Discussions": [
                        {
                            "Discussion_Name": "Evaluation im ISIS-Kurs",
                            "Discussion_Id": "606940",
                            "Messages": [
                                {
                                    "Message_id": "p1088559",
                                    "Author": "Robert Müller",
                                    "DateTime": "2024-07-10T15:29:45+02:00",
                                    "Content": "Liebe Studierende, unabhängig von der bereits durchgeführten Evaluation der Lehrveranstaltung findet auch im ISIS-Kurs noch eine Evaluation statt. Ihr findet diese in unserem ISIS-Kurs im oberen Bereich. Wir würden uns freuen, wenn auch an dieser Evaluation möglichst viele von euch teilnehmen und ihr uns euer Feedback übermittelt. Beste Grüße Robert",
                                    "Response to": "Response to nothing"
                                }
                            ]
                        },
                        {
                            "Discussion_Name": "Tausch VL-UE, 11.7.",
                            "Discussion_Id": "606939",
                            "Messages": [
                                {
                                    "Message_id": "p1088557",
                                    "Author": "Robert Müller",
                                    "DateTime": "2024-07-10T15:18:49+02:00",
                                    "Content": "Liebe Studierende, am morgigen Mittwoch werden wir die Vorlesung und Übung tauschen, d.h. um 10 Uhr findet die Übung statt und nachmittags die Vorlesung. Die Räumen bleiben wie zu den entsprechenden Uhrzeiten gehabt. Beste Grüße Robert",
                                    "Response to": "Response to nothing"
                                }
                            ]
                        },
                        {
                            "Discussion_Name": "Vorlesungsquiz Verbrennung und Dampfkraftwerke",
                            "Discussion_Id": "606153",
                            "Messages": [
                                {
                                    "Message_id": "p1087431",
                                    "Author": "Robert Müller",
                                    "DateTime": "2024-07-08T11:31:06+02:00",
                                    "Content": "Liebe Studierende, ihr findet nun unter dem Link zum Vorlesungsquiz die Frageserien „4. Fossile Brennstoffe und Verbrennung“ und \"5. Dampfkraftwerke\". Bitte bearbeitet beide Frageserien bis zur morgigen Vorlesung am Dienstag. Dort werden die Fragen wieder gemeinsam diskutiert.  Beste Grüße Robert",
                                    "Response to": "This is the original post"
                                },
                                {
                                    "Message_id": "p1087909",
                                    "Author": "Robert Müller",
                                    "DateTime": "2024-07-09T09:35:59+02:00",
                                    "Content": "Hier noch einmal die Erinnerung an das Vorlesungsquiz. Bitte denkt daran, beide Frageserien zu bearbeiten.",
                                    "Response to": "p1087431"
                                }
                            ]
                        },
                        {
                            "Discussion_Name": "Tutorium Montag 14-16 Uhr ",
                            "Discussion_Id": "604537",
                            "Messages": [
                                {
                                    "Message_id": "p1085133",
                                    "Author": "Johann Bollhorst",
                                    "DateTime": "2024-07-01T09:28:04+02:00",
                                    "Content": "Liebe Studis,  aufgrund einer Erkrankung kann das heutige Tutorium von 14 bis 16 Uhr leider nicht stattfinden.   Beste Grüße Johann",
                                    "Response to": "Response to nothing"
                                }
                            ]
                        },
                        {
                            "Discussion_Name": "Vorlesungsquiz Wirtschaftlichkeitsanalyse",
                            "Discussion_Id": "602004",
                            "Messages": [
                                {
                                    "Message_id": "p1081474",
                                    "Author": "Robert Müller",
                                    "DateTime": "2024-06-19T09:53:25+02:00",
                                    "Content": "Liebe Studierende, ihr findet nun unter dem Link zum Vorlesungsquiz die Frageserie „3. Wirtschaftlichkeitsanalyse“. Bitte bearbeitet diese Fragen bis zur Vorlesung am Dienstag. Dort werden die Fragen wieder gemeinsam diskutiert.  Beste Grüße Robert",
                                    "Response to": "This is the original post"
                                },
                                {
                                    "Message_id": "p1083332",
                                    "Author": "Robert Müller",
                                    "DateTime": "2024-06-25T08:51:50+02:00",
                                    "Content": "Hier noch einmal die Erinnerung an das Vorlesungsquiz. Bitte plant genug Zeit ein, da die Frageserie dieses Mal etwas länger ist.",
                                    "Response to": "p1081474"
                                }
                            ]
                        },
                        {
                            "Discussion_Name": "Änderung der Sprechstundenzeit am Montag",
                            "Discussion_Id": "602705",
                            "Messages": [
                                {
                                    "Message_id": "p1082468",
                                    "Author": "Robert Müller",
                                    "DateTime": "2024-06-21T21:16:52+02:00",
                                    "Content": "Liebe Studierende, uns wurde mitgeteilt, dass sich unsere derzeitige Sprechstunde der Assistenten am Montag mit EIS II überschneidet. Wir verschieben daher die Sprechstunde bis zum Ende der Vorlesungszeit auf montags, 13-14 Uhr. Die Sprechstunde findet regulär online über den Link im ISIS-Kurs statt. Wenn ihr in Präsenz zu uns ins KT-Gebäude kommen wollt, dann meldet euch bitte vorab per Email an. Beste Grüße Robert",
                                    "Response to": "Response to nothing"
                                }
                            ]
                        },
                        {
                            "Discussion_Name": "Klausurinfozettel und Altklausurensammlung",
                            "Discussion_Id": "602361",
                            "Messages": [
                                {
                                    "Message_id": "p1081947",
                                    "Author": "Robert Müller",
                                    "DateTime": "2024-06-20T12:18:36+02:00",
                                    "Content": "Liebe Studierende, wie in der heutigen Übung angekündigt, sind auf ISIS nun der Klausurinfozettel sowie die Altklausurensammlung verfügbar. Außerdem ist ab heute die Anmeldung für die Klausur am 24.9. möglich. Studierende mit Ersatzklausuren werden gesondert benachrichtigt. Bitte beachten: Die Altklausuren enthalten sowohl Aufgaben für Energietechnik I als auch Energietechnik II. Die jeweiligen Aufgaben sind der Kreuztabelle zu Beginn jeder Klausur zu entnehmen. Weiterhin sind Aufgaben zur exergoökonomischen NICHT Bestandteil von Energietechnik I. Beste Grüße Robert",
                                    "Response to": "Response to nothing"
                                }
                            ]
                        },
                        {
                            "Discussion_Name": " Vorlesungsquiz - Exergieanalyse Teil III",
                            "Discussion_Id": "597967",
                            "Messages": [
                                {
                                    "Message_id": "p1075582",
                                    "Author": "Robert Müller",
                                    "DateTime": "2024-05-30T16:31:38+02:00",
                                    "Content": "Liebe Studierende, ihr findet nun unter dem Link zum Vorlesungsquiz die Frageserie „2.2 Exergieanalyse - Teil III“. Bitte bearbeitet diese Fragen bis zur Vorlesung am Dienstag. Dort werden die Fragen zusammen mit denen zum zweiten Teil diskutiert.  Beste Grüße Robert",
                                    "Response to": "This is the original post"
                                },
                                {
                                    "Message_id": "p1076672",
                                    "Author": "Robert Müller",
                                    "DateTime": "2024-06-03T21:39:53+02:00",
                                    "Content": "Hier noch mal eine kurze Erinnerung zur Durchführung des aktuellen Vorlesungsquiz.",
                                    "Response to": "p1075582"
                                }
                            ]
                        },
                        {
                            "Discussion_Name": "Aktualisierter Semesterplan",
                            "Discussion_Id": "598051",
                            "Messages": [
                                {
                                    "Message_id": "p1075714",
                                    "Author": "Robert Müller",
                                    "DateTime": "2024-05-31T09:51:28+02:00",
                                    "Content": "Liebe Studierende, es haben sich ein paar Änderungen am Semesterplan ergeben. Die aktualisierte Version findet ihr nun in der Lernumgebung. Weiterhin hat es sich ergeben, dass wir die Übung am Do, 6.6. im gewohnten Raum A 053 durchführen können (entgegen der Ankündigung in der ersten Vorlesung). Beste Grüße Robert",
                                    "Response to": "Response to nothing"
                                }
                            ]
                        },
                        {
                            "Discussion_Name": "Vorlesungsquiz - Exergieanalyse Teil II",
                            "Discussion_Id": "595399",
                            "Messages": [
                                {
                                    "Message_id": "p1071665",
                                    "Author": "Robert Müller",
                                    "DateTime": "2024-05-19T21:46:26+02:00",
                                    "Content": "Liebe Studierende, ihr findet nun unter dem Link zum Vorlesungsquiz die Frageserie „2.2 Exergieanalyse - Teil II“. Bitte bearbeitet diese Fragen bis zur Vorlesung am Dienstag. Dort werden die Fragen wieder diskutiert.  Beste Grüße Robert",
                                    "Response to": "This is the original post"
                                },
                                {
                                    "Message_id": "p1071889",
                                    "Author": "Robert Müller",
                                    "DateTime": "2024-05-21T07:49:45+02:00",
                                    "Content": "Hier noch mal eine kurze Erinnerung zur Durchführung des heutigen Vorlesungsquiz.",
                                    "Response to": "p1071665"
                                }
                            ]
                        },
                        {
                            "Discussion_Name": "Freie Stelle als studentische Hilfskraft (Technische Wärmelehre)",
                            "Discussion_Id": "594994",
                            "Messages": [
                                {
                                    "Message_id": "p1070997",
                                    "Author": "Robert Müller",
                                    "DateTime": "2024-05-16T15:59:13+02:00",
                                    "Content": "Liebe Studierende, wir sind auf der Suche nach einer studentischen Hilfskraft mit Unterrichtsaufgaben (Tutor:in) für die Lehrveranstaltung Technische Wärmelehre I+II. Die Veranstaltung ist inhaltlich sehr ähnlich zu Thermodynamik I und wird vor allem für Wi-Ings angeboten. Aktuell wird sie noch von Professor Ziegler gehalten, wird aber ab nächstem Semester von unserem Fachgebiet angeboten. Wer Interesse hat kann sich gerne bei uns melden (auch für weitere Infos). Aus organisatorischen Gründen bitte noch heute oder morgen. Beste Grüße Robert",
                                    "Response to": "This is the original post"
                                },
                                {
                                    "Message_id": "p1071360",
                                    "Author": "Robert Müller",
                                    "DateTime": "2024-05-17T15:54:24+02:00",
                                    "Content": "Nachtrag: Man muss für die Stelle selber nicht Wirtschaftsingenieurwesen studieren. Studierende aller Studiengänge sind willkommen, es sollte nur Thermodynamik oder TWL oder ähnliches gehört worden sein. Bei Interesse gerne E-Mail mit Lebenslauf und aktueller Notenbescheinigung an:  robert.mueller.2@@tu-berlin.de  Beste Grüße Robert",
                                    "Response to": "p1070997"
                                }
                            ]
                        },
                        {
                            "Discussion_Name": "Tutorium Mittwoch 14-16 Uhr",
                            "Discussion_Id": "594603",
                            "Messages": [
                                {
                                    "Message_id": "p1070419",
                                    "Author": "Johann Bollhorst",
                                    "DateTime": "2024-05-15T11:56:55+02:00",
                                    "Content": "Liebe Studis,  das Tutorium am Mittwoch findet weiterhin statt. Erscheint bis 15 min nach Beginn des Tutoriums kein Studi, wird das Tutorium beendet. Ihr könnt mir auch gerne eine Nachricht per Mail oder ISIS schreiben, falls ihr es nicht rechtzeitig schaffen solltet. Beste Grüße Johann",
                                    "Response to": "Response to nothing"
                                }
                            ]
                        },
                        {
                            "Discussion_Name": "Tutorium am Mittwoch von 10-12 Uhr",
                            "Discussion_Id": "594213",
                            "Messages": [
                                {
                                    "Message_id": "p1069797",
                                    "Author": "Dara Gelli",
                                    "DateTime": "2024-05-14T06:07:01+02:00",
                                    "Content": "Liebe Studierende,  Das Tutorium am Mittwoch von 10 bis 12 Uhr findet AB DIESER WOCHE DAUERHAFT in KT 202 statt. Alle anderen Termine und jeweiligen Räume bleiben unverändert!  Beste Grüße und bis dahin Dara",
                                    "Response to": "Response to nothing"
                                }
                            ]
                        },
                        {
                            "Discussion_Name": " Quiz zur Vorlesung",
                            "Discussion_Id": "591807",
                            "Messages": [
                                {
                                    "Message_id": "p1065971",
                                    "Author": "Robert Müller",
                                    "DateTime": "2024-05-02T16:15:36+02:00",
                                    "Content": "Liebe Studierende, ihr findet nun im Abschnitt \"Vorlesungsunterlagen\" das Vorlesungsquiz. Wenn ihr den Link dort aufruft, gelangt ihr zum Umfragetool Particify. Wir möchten euch bitten, dort bis zur Vorlesung am Dienstag unter \"Energietechnik I - Vorlesung\" die Frageserie \"2.2 Exergieanalyse - Teil I\" zu bearbeiten. Es handelt sich um 10 kurze Fragen, die sowohl an mobilen Endgeräten als auch am PC/Laptop bearbeitet werden können. Bitte beantwortet diese Fragen, nachdem ihr den Inhalt, der am Dienstag in der Vorlesung behandelt wurde, noch einmal selbstständig durchgegangen seid und ohne den Inhalt bei der Beantwortung der Fragen zu konsultieren. Das Quiz ist kein Test, es ist anonym und nur zur Übung der behandelten Inhalte gedacht. Am Dienstag werden die Fragen und Antworten dann in der Vorlesung diskutiert. Ihr habt so die Möglichkeit, herauszufinden und Feedback dazu zu geben, was ihr schon gut verstanden habt und was nicht. Viel Spaß und beste Grüße Robert",
                                    "Response to": "This is the original post"
                                },
                                {
                                    "Message_id": "p1067063",
                                    "Author": "Robert Müller",
                                    "DateTime": "2024-05-06T10:46:22+02:00",
                                    "Content": "Liebe Studierende,  hier noch einmal die Erinnerung daran, bitte bis morgen zur Vorlesung das Quiz durchzuführen.  Beste Grüße Robert",
                                    "Response to": "p1065971"
                                },
                                {
                                    "Message_id": "p1067569",
                                    "Author": "Robert Müller",
                                    "DateTime": "2024-05-07T09:24:36+02:00",
                                    "Content": "Und auch heute noch mal eine Erinnerung an das Quiz. Da dieses nachher in der Vorlesung besprochen wird, sollten alle bis dahin daran teilgenommen haben.  Beste Grüße Robert",
                                    "Response to": "p1067063"
                                }
                            ]
                        },
                        {
                            "Discussion_Name": "ACHTUNG! Heute findet keine Vorlesung statt.",
                            "Discussion_Id": "591569",
                            "Messages": [
                                {
                                    "Message_id": "p1065620",
                                    "Author": "Fontina Petrakopoulou",
                                    "DateTime": "2024-05-02T09:18:47+02:00",
                                    "Content": "Wie bereits am Dienstag mitgeteilt heute findet keine Vorlesung statt. Wir sehen uns wieder am Dienstag 7.5 im C130.  Schöne Grüße, Fontina Petrakopoulou",
                                    "Response to": "Response to nothing"
                                }
                            ]
                        },
                        {
                            "Discussion_Name": "ACHTUNG: Dienstagsvorlesung ab morgen(!), 30.4.2024 von 12-14 Uhr im C 130",
                            "Discussion_Id": "590718",
                            "Messages": [
                                {
                                    "Message_id": "p1064317",
                                    "Author": "Robert Müller",
                                    "DateTime": "2024-04-29T12:01:45+02:00",
                                    "Content": "Liebe Studierende, es hat sich kurzfristig ergeben, dass wir doch schon ab morgen (30.4.) den Vorlesungstermin und -raum wechseln können: Die Dienstagsvorlesung findet ab morgen immer von 12-14 Uhr im C 130 statt. Meine vorherige Nachricht bitte ignorieren. Beste Grüße Robert",
                                    "Response to": "This is the original post"
                                },
                                {
                                    "Message_id": "p1064434",
                                    "Author": "Robert Müller",
                                    "DateTime": "2024-04-29T14:08:09+02:00",
                                    "Content": "Weitere Info:  Das Dienstagstutorium verschiebt sich somit auf 10-12 Uhr und findet nun im KT 101 statt.  Der Wochenplan ist entsprechend aktualisiert.  Beste Grüße Robert",
                                    "Response to": "p1064317"
                                }
                            ]
                        },
                        {
                            "Discussion_Name": "Tutorium am Montag von 14-16 Uhr",
                            "Discussion_Id": "590704",
                            "Messages": [
                                {
                                    "Message_id": "p1064290",
                                    "Author": "Robert Müller",
                                    "DateTime": "2024-04-29T11:27:03+02:00",
                                    "Content": "Liebe Studierende, bei der Tutorienanmeldung hatte sich ein kleiner Fehler eingeschlichen: Das Montagstutorium findet von 14-16 Uhr statt - so, wie es auch im Wochenplan steht. Wir bitten die Unklarheit zu entschuldigen. Beste Grüße Robert",
                                    "Response to": "Response to nothing"
                                }
                            ]
                        },
                        {
                            "Discussion_Name": "Verlegung der Dienstagsvorlesung wird verschoben",
                            "Discussion_Id": "588342",
                            "Messages": [
                                {
                                    "Message_id": "p1060650",
                                    "Author": "Robert Müller",
                                    "DateTime": "2024-04-22T11:59:49+02:00",
                                    "Content": "Liebe Studierende, leider müssen wir die Verlegung der Vorlesung am Dienstag noch einmal verschieben, das es Probleme bei der Raumbuchung gibt. Die morgige Vorlesung (23.04.) wird daher wie gewohnt um 10 Uhr im A 053 stattfinden. Ob wir die Vorlesung zukünftig zu einem anderen Termin anbieten können, werden wir voraussichtlich bis nächste Woche erfahren. Wir werden daher zunächst die Tutorientermine wie ursprünglich geplant belassen und ggf. später Anpassungen vornehmen. Beste Grüße Robert",
                                    "Response to": "Response to nothing"
                                }
                            ]
                        },
                        {
                            "Discussion_Name": "Verschiebung der Tutorienanmeldung",
                            "Discussion_Id": "587434",
                            "Messages": [
                                {
                                    "Message_id": "p1059180",
                                    "Author": "Robert Müller",
                                    "DateTime": "2024-04-18T17:19:26+02:00",
                                    "Content": "Liebe Studierende, da wir wie in der Vorlesung angekündigt versuchen werden, die Dienstags-VL auf 12-14 Uhr zu verlegen (vorbehaltlich der Bestätigung durch innoCampus), ergeben sich noch kleine Änderungen bei den Tutorienterminen. Wir verschieben daher den Start der Tutorienanmeldung auf Montag, 22.4., 18 Uhr. Wir werden über die Änderungen noch einmal separat informieren. Beste Grüße Robert",
                                    "Response to": "Response to nothing"
                                }
                            ]
                        }
                    ]
                }
            ],
            [
                {
                    "Forum_name": "Studiforum",
                    "Forum_id": "1791719",
                    "Discussions": [
                        {
                            "Discussion_Name": "Übung heute",
                            "Discussion_Id": "602324",
                            "Messages": [
                                {
                                    "Message_id": "p1081897",
                                    "Author": "Alper Kaya",
                                    "DateTime": "2024-06-20T11:06:49+02:00",
                                    "Content": "Hallo, in welchem Raum findet heute die Übung statt? Letzte Woche wurde etwas angekündigt, jedoch steht auf ISIS nichts dazu. LG",
                                    "Response to": "This is the original post"
                                },
                                {
                                    "Message_id": "p1081931",
                                    "Author": "Robert Müller",
                                    "DateTime": "2024-06-20T11:54:32+02:00",
                                    "Content": "Die Übung heute Nachnmittag findet wie immer im A 053 statt.  Heute Vormittag gab es anstatt der Vorlesung ebenfalls eine Übung. Vielleicht meintest du das.",
                                    "Response to": "p1081897"
                                }
                            ]
                        },
                        {
                            "Discussion_Name": "E-Kreide Übungen",
                            "Discussion_Id": "598363",
                            "Messages": [
                                {
                                    "Message_id": "p1076177",
                                    "Author": "Jannis Max Lenke",
                                    "DateTime": "2024-06-02T19:11:31+02:00",
                                    "Content": "Hi ich wollte nachfragen ob noch die E-Kreide aus den letzten Übungen hochgeladen werden können?",
                                    "Response to": "This is the original post"
                                },
                                {
                                    "Message_id": "p1076347",
                                    "Author": "Robert Müller",
                                    "DateTime": "2024-06-03T11:11:36+02:00",
                                    "Content": "Hallo Jannis,  danke für den Hinweis! Die E-Kreiden der 7. Übung sind jetzt hochgeladen, die der 8. folgt später noch.  Beste Grüße Robert",
                                    "Response to": "p1076177"
                                }
                            ]
                        },
                        {
                            "Discussion_Name": "Tutorium Mi 14-16 Uhr",
                            "Discussion_Id": "593319",
                            "Messages": [
                                {
                                    "Message_id": "p1068345",
                                    "Author": "Johann Bollhorst",
                                    "DateTime": "2024-05-08T15:41:07+02:00",
                                    "Content": "Liebe Studis,  vorhin hing noch fälschlicherweise am KT101, dass das ET Tutorium im Raum KT202 stattfindet. Hierfür möchten wir uns entschuldigen. Falls ihr dadurch das Tutorium nicht wahrnehmen konntet, besteht für euch noch die Möglichkeit das Tutorium am Freitag bei Dara zu besuchen. Da sich auch nur zwei Leute für diesen Termin angemeldet haben, möchten wir zudem abfragen, ob weiterhin Interesse an diesem Termin besteht, andererseits würden wir den Termin nicht weiter anbieten. Schreibt mir dazu eine kurze Nachricht bei ISIS oder per Mail.  Solltet ihr den Termin am Freitag nicht wahrnehmen können, dann könnt ihr in eine der beiden Sprechstunden oder in den Tutorien nächste Woche eure Fragen bezüglich des Tutoriums stellen. Beste Grüße  Johann ",
                                    "Response to": "Response to nothing"
                                }
                            ]
                        },
                        {
                            "Discussion_Name": "Sprechstunde heute KT2",
                            "Discussion_Id": "591678",
                            "Messages": [
                                {
                                    "Message_id": "p1065782",
                                    "Author": "Alper Kaya",
                                    "DateTime": "2024-05-02T12:16:15+02:00",
                                    "Content": "Hallo, findet die Sprechstunde heute statt?  LG",
                                    "Response to": "This is the original post"
                                },
                                {
                                    "Message_id": "p1065825",
                                    "Author": "Johann Bollhorst",
                                    "DateTime": "2024-05-02T13:00:01+02:00",
                                    "Content": "Hallo Alper,  ja, die Sprechstunde findet heute statt.  Beste Grüße Johann",
                                    "Response to": "p1065782"
                                }
                            ]
                        },
                        {
                            "Discussion_Name": "Tutorium",
                            "Discussion_Id": "590110",
                            "Messages": [
                                {
                                    "Message_id": "p1063392",
                                    "Author": "Jonel Pojani",
                                    "DateTime": "2024-04-26T10:47:06+02:00",
                                    "Content": "Hallo,  gibt es kein Tutorium heute an der EN Gebäude?(10-12) Vielen Dank ",
                                    "Response to": "This is the original post"
                                },
                                {
                                    "Message_id": "p1063406",
                                    "Author": "Johann Bollhorst",
                                    "DateTime": "2024-04-26T11:01:36+02:00",
                                    "Content": "Hallo Jonel,  die Tutorien beginnen erst nächste Woche.  Beste Grüße Johann",
                                    "Response to": "p1063392"
                                }
                            ]
                        },
                        {
                            "Discussion_Name": "Vorlesung ",
                            "Discussion_Id": "589672",
                            "Messages": [
                                {
                                    "Message_id": "p1062745",
                                    "Author": "Nader Atallah",
                                    "DateTime": "2024-04-25T10:00:52+02:00",
                                    "Content": "Findet heute keine Vorlesung statt in EW 203 ?",
                                    "Response to": "This is the original post"
                                },
                                {
                                    "Message_id": "p1062762",
                                    "Author": "Florian Geißler",
                                    "DateTime": "2024-04-25T10:18:59+02:00",
                                    "Content": "yep",
                                    "Response to": "p1062745"
                                }
                            ]
                        },
                        {
                            "Discussion_Name": "Whatsapp Gruppe",
                            "Discussion_Id": "589629",
                            "Messages": [
                                {
                                    "Message_id": "p1062680",
                                    "Author": "Ratu Ersya Aqilla",
                                    "DateTime": "2024-04-25T06:24:58+02:00",
                                    "Content": "Hallo, gibt‘s schon eine Whatsapp Gruppe für dieses Modul? :)",
                                    "Response to": "Response to nothing"
                                }
                            ]
                        },
                        {
                            "Discussion_Name": "Zwei Übungen ein Inhalt?",
                            "Discussion_Id": "585274",
                            "Messages": [
                                {
                                    "Message_id": "p1056038",
                                    "Author": "Florian Geißler",
                                    "DateTime": "2024-04-10T13:35:52+02:00",
                                    "Content": "Halli hallo, ist der Inhalt \"der Übung\" für beide Termine in einer Woche der selbe? Kann man sich somit also aussuchen, welchen der beiden Termine man besucht oder gilt es beide Termine wahrzunehmen? Danke und liebe Grüße Florian :)",
                                    "Response to": "This is the original post"
                                },
                                {
                                    "Message_id": "p1056126",
                                    "Author": "Robert Müller",
                                    "DateTime": "2024-04-10T17:32:18+02:00",
                                    "Content": "Hallo Florian,  nein, in jedem Übungstermin gibt es neue (oder fortgesetzte) Inhalte, es sollte also jeder Termin wahrgenommen werden.  Beste Grüße Robert",
                                    "Response to": "p1056038"
                                },
                                {
                                    "Message_id": "p1056152",
                                    "Author": "Florian Geißler",
                                    "DateTime": "2024-04-10T19:16:12+02:00",
                                    "Content": "Alles klar, vielen Dank :)",
                                    "Response to": "p1056126"
                                }
                            ]
                        }
                    ]
                }
            ]
        ]
    }
]